{
  "configVersion": 1,
  "timestamp": 1607632270555,
  "index": "/index.html",
  "assetGroups": [
    {
      "name": "app",
      "installMode": "prefetch",
      "updateMode": "prefetch",
      "cacheQueryOptions": {
        "ignoreVary": true
      },
      "urls": [
        "/6-es2015.82717d15f911baf7599d.js",
        "/6-es5.82717d15f911baf7599d.js",
        "/7-es2015.8e1c8c8525cf93d93fa5.js",
        "/7-es5.8e1c8c8525cf93d93fa5.js",
        "/8-es2015.0303aba186dbc6c08939.js",
        "/8-es5.0303aba186dbc6c08939.js",
        "/9-es2015.0f4f15343a40c10a1907.js",
        "/9-es5.0f4f15343a40c10a1907.js",
        "/common-es2015.888ac96e89d69bf51a1f.js",
        "/common-es5.888ac96e89d69bf51a1f.js",
        "/favicon.ico",
        "/index.html",
        "/main-es2015.a4e4ddc98fca0c3dc59d.js",
        "/main-es5.a4e4ddc98fca0c3dc59d.js",
        "/manifest.webmanifest",
        "/polyfills-es2015.008b96fa1b5dc34a4400.js",
        "/polyfills-es5.c54b07b6d332c149dea2.js",
        "/runtime-es2015.f79fbfceec3a95e80643.js",
        "/runtime-es5.f79fbfceec3a95e80643.js",
        "/styles.c31e038c3331bc1649c6.css"
      ],
      "patterns": []
    },
    {
      "name": "assets",
      "installMode": "lazy",
      "updateMode": "prefetch",
      "cacheQueryOptions": {
        "ignoreVary": true
      },
      "urls": [
        "/assets/icons/icon-152x152.png",
        "/assets/icons/icon-16x16.png",
        "/assets/icons/icon-192x192.png",
        "/assets/icons/icon-32x32.png",
        "/assets/icons/icon-384x384.png",
        "/assets/icons/icon-512x512.png",
        "/assets/images/butter.png",
        "/fa-brands-400.0fea24969112a781acd2.eot",
        "/fa-brands-400.c967a94cfbe2b06627ff.woff2",
        "/fa-brands-400.dc2cbadd690e1d4b2c9c.woff",
        "/fa-brands-400.e33e2cf6e02cac2ccb77.svg",
        "/fa-brands-400.ec82f282c7f54b637098.ttf",
        "/fa-regular-400.06b9d19ced8d17f3d5cb.svg",
        "/fa-regular-400.08f9891a6f44d9546678.eot",
        "/fa-regular-400.1008b5226941c24f4468.woff2",
        "/fa-regular-400.1069ea55beaa01060302.woff",
        "/fa-regular-400.1495f578452eb676f730.ttf",
        "/fa-solid-900.10ecefc282f2761808bf.ttf",
        "/fa-solid-900.371dbce0dd46bd4d2033.svg",
        "/fa-solid-900.3a24a60e7f9c6574864a.eot",
        "/fa-solid-900.3ceb50e7bcafb577367c.woff2",
        "/fa-solid-900.46fdbd2d897f8824e63c.woff"
      ],
      "patterns": []
    }
  ],
  "dataGroups": [],
  "hashTable": {
    "/6-es2015.82717d15f911baf7599d.js": "12082410623a8a84a047a117f8a3106d1e75a20e",
    "/6-es5.82717d15f911baf7599d.js": "8176dc7e94b7d07b76afbf6d44b2e0e1fdc3aea8",
    "/7-es2015.8e1c8c8525cf93d93fa5.js": "d2341e553984fa249e6981d906d861dce5828a65",
    "/7-es5.8e1c8c8525cf93d93fa5.js": "53e019aebacdf2cfcc67232d9c25f13d608a0635",
    "/8-es2015.0303aba186dbc6c08939.js": "6bc0674b5bb98fc0f1cacd7e2be0c24b7f8c7b31",
    "/8-es5.0303aba186dbc6c08939.js": "56465898efce2b55d3e62cb6cd0b62ffa9a10f1c",
    "/9-es2015.0f4f15343a40c10a1907.js": "ca43557b44d432d8dbcb6f14be129a4081214541",
    "/9-es5.0f4f15343a40c10a1907.js": "01426df1a133566460f1e632e8bbab57ff6c6307",
    "/assets/icons/icon-152x152.png": "0636dd3479c2b3892986241557fe70ff51b3886e",
    "/assets/icons/icon-16x16.png": "94001dcd0b53c90083237681bf113b5d714f46b0",
    "/assets/icons/icon-192x192.png": "3cd673c12c0ce2a0d3f5da1fe52c4f4620f06df6",
    "/assets/icons/icon-32x32.png": "ffe436a5fd36797f14caed28e891c074c0ce328d",
    "/assets/icons/icon-384x384.png": "31d322f7e927808f3103d668ff6c9d22b7b7da0f",
    "/assets/icons/icon-512x512.png": "eea66e6c341bf1b6007aa5222eead313331340e9",
    "/assets/images/butter.png": "6afc6c1cf4b7dcb37c61a7996de80d8d938e6052",
    "/common-es2015.888ac96e89d69bf51a1f.js": "9806f163c9fb04f303ad6e8ce2fe348196c80644",
    "/common-es5.888ac96e89d69bf51a1f.js": "e1af9418dc8b29688e356acd338836e6b909cc98",
    "/fa-brands-400.0fea24969112a781acd2.eot": "c719f4375679ee58e156434f9ba9727be669cf07",
    "/fa-brands-400.c967a94cfbe2b06627ff.woff2": "f726c4275bb494a045fde059175f072de06c01df",
    "/fa-brands-400.dc2cbadd690e1d4b2c9c.woff": "a42ac4a94f4e0e9333cdb1b2fb6c13c0ae690ff2",
    "/fa-brands-400.e33e2cf6e02cac2ccb77.svg": "69a0ff79a9d93a451e9fa90bd79ae7008d2a9da5",
    "/fa-brands-400.ec82f282c7f54b637098.ttf": "9b49c6c5b0cbdef158ae31b2a4e4814555408389",
    "/fa-regular-400.06b9d19ced8d17f3d5cb.svg": "c41a688158d577e3a2738137992d49b05b17ab8f",
    "/fa-regular-400.08f9891a6f44d9546678.eot": "2baa9a8aa68f1d2d4712b3c7205f9105aaf21879",
    "/fa-regular-400.1008b5226941c24f4468.woff2": "fb9648469530a05fa9aac80e47d4d6960472a242",
    "/fa-regular-400.1069ea55beaa01060302.woff": "26afc29d39ab9fac6d0b607be7e76db093ff7c3a",
    "/fa-regular-400.1495f578452eb676f730.ttf": "d64e58981a419de52bac110c979887d34e366135",
    "/fa-solid-900.10ecefc282f2761808bf.ttf": "d537bf4cc7273ddb3fd754d53f2b241aeafaefe7",
    "/fa-solid-900.371dbce0dd46bd4d2033.svg": "36de6a298660ed3feaab37900f7b28c3e981d80e",
    "/fa-solid-900.3a24a60e7f9c6574864a.eot": "c39b89f7fa7b66931ab02a54002db5ffcbff206c",
    "/fa-solid-900.3ceb50e7bcafb577367c.woff2": "9b592048b9062b00f0b2dd782d70a95b7dc69b83",
    "/fa-solid-900.46fdbd2d897f8824e63c.woff": "3b86a0ce15d8d534b65e98560e321a933d310688",
    "/favicon.ico": "c3c1192704689dddb2315364a2b8edbf0f488985",
    "/index.html": "beac9b79f8360010779f6532a3042e0ff12babc5",
    "/main-es2015.a4e4ddc98fca0c3dc59d.js": "87efcd8684dcb6a5c77bb4e12c89bb97c4a34b37",
    "/main-es5.a4e4ddc98fca0c3dc59d.js": "1e2e83c1d509e9dfb077a4fe125cce0f907e1d51",
    "/manifest.webmanifest": "54489f5c19b1406c94c13aabcc1026bc46472810",
    "/polyfills-es2015.008b96fa1b5dc34a4400.js": "144b477e8e533ea5b5e71c1061731bf53a69862c",
    "/polyfills-es5.c54b07b6d332c149dea2.js": "7a16aca9dd3f0d86e36f69623813db084121e56e",
    "/runtime-es2015.f79fbfceec3a95e80643.js": "c491c22a869013798cc6d86b75b43aac34c83958",
    "/runtime-es5.f79fbfceec3a95e80643.js": "cd5372bafa7bf0675f7778b760a8fd95f3594631",
    "/styles.c31e038c3331bc1649c6.css": "6d5a1a7962a2b4315dbc45baf11a6a0e2850949f"
  },
  "navigationUrls": [
    {
      "positive": true,
      "regex": "^\\/.*$"
    },
    {
      "positive": false,
      "regex": "^\\/(?:.+\\/)?[^/]*\\.[^/]*$"
    },
    {
      "positive": false,
      "regex": "^\\/(?:.+\\/)?[^/]*__[^/]*$"
    },
    {
      "positive": false,
      "regex": "^\\/(?:.+\\/)?[^/]*__[^/]*\\/.*$"
    }
  ]
}